eoplatform/__init__.py
eoplatform/__main__.py
eoplatform/auto_import.py
eoplatform/cli.py
eoplatform/composites/__init__.py
eoplatform/composites/classes.py
eoplatform/composites/factory.py
eoplatform/composites/generator.py
eoplatform/composites/interface.py
eoplatform/composites/safe_eval.py
eoplatform/composites/visualizers.py
eoplatform/console.py
eoplatform/data/composites/ARI.json
eoplatform/data/composites/ARVI.json
eoplatform/data/composites/ATSAVI.json
eoplatform/data/composites/AWEInsh.json
eoplatform/data/composites/AWEIsh.json
eoplatform/data/composites/BAI.json
eoplatform/data/composites/BAIS2.json
eoplatform/data/composites/BNDVI.json
eoplatform/data/composites/BWDRVI.json
eoplatform/data/composites/CIG.json
eoplatform/data/composites/CIRE.json
eoplatform/data/composites/CSIT.json
eoplatform/data/composites/CVI.json
eoplatform/data/composites/DVI.json
eoplatform/data/composites/EBBI.json
eoplatform/data/composites/EVI.json
eoplatform/data/composites/EVI2.json
eoplatform/data/composites/ExG.json
eoplatform/data/composites/GARI.json
eoplatform/data/composites/GBNDVI.json
eoplatform/data/composites/GDVI.json
eoplatform/data/composites/GEMI.json
eoplatform/data/composites/GLI.json
eoplatform/data/composites/GNDVI.json
eoplatform/data/composites/GRNDVI.json
eoplatform/data/composites/GVMI.json
eoplatform/data/composites/IRECI.json
eoplatform/data/composites/kEVI.json
eoplatform/data/composites/kNDVI.json
eoplatform/data/composites/kRVI.json
eoplatform/data/composites/kVARI.json
eoplatform/data/composites/MCARI.json
eoplatform/data/composites/MCARI1.json
eoplatform/data/composites/MCARI2.json
eoplatform/data/composites/MGRVI.json
eoplatform/data/composites/MNDVI.json
eoplatform/data/composites/MNDWI.json
eoplatform/data/composites/MNLI.json
eoplatform/data/composites/MSAVI.json
eoplatform/data/composites/MSR.json
eoplatform/data/composites/MTCI.json
eoplatform/data/composites/MTVI1.json
eoplatform/data/composites/MTVI2.json
eoplatform-0.2.4.dist-info/entry_points.txt
eoplatform-0.2.4.dist-info/LICENSE
eoplatform-0.2.4.dist-info/WHEEL
eoplatform-0.2.4.dist-info/METADATA
eoplatform-0.2.4.dist-info/RECORD
