Metadata-Version: 2.1
Name: eoplatform
Version: 0.2.4
Summary: Earth Observation made easy.
Home-page: https://github.com/mtralka/EOPlatform
License: GPL-3.0-only
Keywords: remote sensing,earth observation,gis,education
Author: Matthew Tralka
Author-email: matthew@tralka.xyz
Maintainer: Matthew Tralka
Maintainer-email: matthew@tralka.xyz
Requires-Python: >=3.8,<3.11
Classifier: Development Status :: 4 - Beta
Classifier: Intended Audience :: Developers
Classifier: Intended Audience :: Education
Classifier: Intended Audience :: Science/Research
Classifier: License :: OSI Approved :: GNU General Public License v3 (GPLv3)
Classifier: Programming Language :: Python :: 3
Classifier: Programming Language :: Python :: 3.10
Classifier: Programming Language :: Python :: 3.8
Classifier: Programming Language :: Python :: 3.9
Requires-Dist: numpy (>=1.21.3,<2.0.0)
Requires-Dist: rich (>=10.12.0,<11.0.0)
Requires-Dist: typer[all] (>=0.4.0,<0.5.0)
Project-URL: Repository, https://github.com/mtralka/EOPlatform
